dsrnascan/__init__.py
dsrnascan/browse_results.py
dsrnascan/compile_einverted.py
dsrnascan/dsRNAscan.py
dsrnascan/fix_einverted_paths.py
dsrnascan/tools/einverted
dsrnascan/tools/platform_binaries/einverted_linux_arm64
dsrnascan/tools/platform_binaries/einverted_linux_x86_64
dsrnascan/tools/platform_binaries/einverted_macos_arm64
dsrnascan/tools/platform_binaries/einverted_macos_x86_64
dsrnascan/tools/platform_binaries/einverted_windows_x86_64.exe
dsrnascan-0.4.6.dist-info/licenses/LICENSE
dsrnascan-0.4.6.dist-info/METADATA
dsrnascan-0.4.6.dist-info/WHEEL
dsrnascan-0.4.6.dist-info/entry_points.txt
dsrnascan-0.4.6.dist-info/top_level.txt
dsrnascan-0.4.6.dist-info/RECORD
