Metadata-Version: 2.4
Name: dsrnascan
Version: 0.4.6
Summary: A tool for genome-wide prediction of double-stranded RNA structures
Home-page: https://github.com/Bass-Lab/dsRNAscan
Author: Bass Lab
Author-email: 
License: GPL-3.0-or-later
Project-URL: Homepage, https://github.com/Bass-Lab/dsRNAscan
Project-URL: Documentation, https://github.com/Bass-Lab/dsRNAscan/blob/main/README.md
Project-URL: Repository, https://github.com/Bass-Lab/dsRNAscan
Project-URL: Bug Tracker, https://github.com/Bass-Lab/dsRNAscan/issues
Keywords: bioinformatics,RNA,dsRNA,secondary structure,genomics
Classifier: Development Status :: 4 - Beta
Classifier: Intended Audience :: Science/Research
Classifier: Topic :: Scientific/Engineering :: Bio-Informatics
Classifier: License :: OSI Approved :: GNU General Public License v3 or later (GPLv3+)
Classifier: Programming Language :: Python :: 3
Classifier: Programming Language :: Python :: 3.8
Classifier: Programming Language :: Python :: 3.9
Classifier: Programming Language :: Python :: 3.10
Classifier: Programming Language :: Python :: 3.11
Classifier: Programming Language :: Python :: 3.12
Classifier: Operating System :: POSIX :: Linux
Classifier: Operating System :: MacOS :: MacOS X
Requires-Python: >=3.8
License-File: LICENSE
Requires-Dist: biopython>=1.78
Requires-Dist: numpy>=1.19
Requires-Dist: pandas>=1.1
Requires-Dist: ViennaRNA>=2.4
Requires-Dist: psutil>=5.8
Provides-Extra: mpi
Requires-Dist: mpi4py>=3.0; extra == "mpi"
Requires-Dist: parasail>=1.2; extra == "mpi"
Provides-Extra: dev
Requires-Dist: pytest>=6.0; extra == "dev"
Requires-Dist: pytest-cov>=2.0; extra == "dev"
Requires-Dist: black>=22.0; extra == "dev"
Requires-Dist: flake8>=4.0; extra == "dev"
Requires-Dist: mypy>=0.900; extra == "dev"
Dynamic: home-page
Dynamic: license-file
Dynamic: requires-python
